<?xml version="1.0" standalone="yes"?>
<MdbTranslationStore xmlns="http://tempuri.org/MdbTranslationStore.xsd">
  <GeneralIds>
    <StringID>1</StringID>
  </GeneralIds>
  <GeneralIds>
    <StringID>2</StringID>
  </GeneralIds>
  <GeneralIds>
    <StringID>3</StringID>
  </GeneralIds>
  <GeneralIds>
    <StringID>4</StringID>
  </GeneralIds>
  <GeneralIds>
    <StringID>5</StringID>
  </GeneralIds>
  <GeneralIds>
    <StringID>6</StringID>
  </GeneralIds>
  <GeneralIds>
    <StringID>7</StringID>
  </GeneralIds>
  <GeneralIds>
    <StringID>8</StringID>
  </GeneralIds>
  <GeneralIds>
    <StringID>9</StringID>
  </GeneralIds>
  <GeneralIds>
    <StringID>10</StringID>
  </GeneralIds>
  <GeneralIds>
    <StringID>11</StringID>
  </GeneralIds>
  <GeneralIds>
    <StringID>12</StringID>
  </GeneralIds>
  <GeneralIds>
    <StringID>13</StringID>
  </GeneralIds>
  <GeneralIds>
    <StringID>14</StringID>
  </GeneralIds>
  <GeneralIds>
    <StringID>15</StringID>
  </GeneralIds>
  <GeneralIds>
    <StringID>16</StringID>
  </GeneralIds>
  <GeneralIds>
    <StringID>17</StringID>
  </GeneralIds>
  <GeneralIds>
    <StringID>18</StringID>
  </GeneralIds>
  <GeneralIds>
    <StringID>19</StringID>
  </GeneralIds>
  <GeneralIds>
    <StringID>20</StringID>
  </GeneralIds>
  <GeneralIds>
    <StringID>21</StringID>
  </GeneralIds>
  <GeneralIds>
    <StringID>22</StringID>
  </GeneralIds>
  <GeneralIds>
    <StringID>23</StringID>
  </GeneralIds>
  <GeneralIds>
    <StringID>24</StringID>
  </GeneralIds>
  <GeneralIds>
    <StringID>25</StringID>
  </GeneralIds>
  <GeneralIds>
    <StringID>26</StringID>
  </GeneralIds>
  <GeneralIds>
    <StringID>27</StringID>
  </GeneralIds>
  <GeneralIds>
    <StringID>28</StringID>
  </GeneralIds>
  <GeneralIds>
    <StringID>29</StringID>
  </GeneralIds>
  <GeneralIds>
    <StringID>30</StringID>
  </GeneralIds>
  <GeneralIds>
    <StringID>31</StringID>
  </GeneralIds>
  <GeneralIds>
    <StringID>32</StringID>
  </GeneralIds>
  <GeneralIds>
    <StringID>33</StringID>
  </GeneralIds>
  <GeneralIds>
    <StringID>34</StringID>
  </GeneralIds>
  <GeneralIds>
    <StringID>35</StringID>
  </GeneralIds>
  <GeneralIds>
    <StringID>36</StringID>
  </GeneralIds>
  <GeneralIds>
    <StringID>37</StringID>
  </GeneralIds>
  <GeneralIds>
    <StringID>38</StringID>
  </GeneralIds>
  <GeneralIds>
    <StringID>39</StringID>
  </GeneralIds>
  <GeneralIds>
    <StringID>40</StringID>
  </GeneralIds>
  <GeneralIds>
    <StringID>41</StringID>
  </GeneralIds>
  <GeneralIds>
    <StringID>42</StringID>
  </GeneralIds>
  <GeneralIds>
    <StringID>43</StringID>
  </GeneralIds>
  <GeneralIds>
    <StringID>44</StringID>
  </GeneralIds>
  <GeneralIds>
    <StringID>45</StringID>
  </GeneralIds>
  <GeneralIds>
    <StringID>46</StringID>
  </GeneralIds>
  <GeneralIds>
    <StringID>47</StringID>
  </GeneralIds>
  <GeneralIds>
    <StringID>48</StringID>
  </GeneralIds>
  <GeneralIds>
    <StringID>49</StringID>
  </GeneralIds>
  <GeneralIds>
    <StringID>50</StringID>
  </GeneralIds>
  <GeneralIds>
    <StringID>51</StringID>
  </GeneralIds>
  <GeneralIds>
    <StringID>52</StringID>
  </GeneralIds>
  <GeneralIds>
    <StringID>53</StringID>
  </GeneralIds>
  <GeneralIds>
    <StringID>54</StringID>
  </GeneralIds>
  <GeneralIds>
    <StringID>55</StringID>
  </GeneralIds>
  <GeneralIds>
    <StringID>56</StringID>
  </GeneralIds>
  <GeneralIds>
    <StringID>57</StringID>
  </GeneralIds>
  <GeneralIds>
    <StringID>58</StringID>
  </GeneralIds>
  <GeneralIds>
    <StringID>59</StringID>
  </GeneralIds>
  <GeneralIds>
    <StringID>60</StringID>
  </GeneralIds>
  <GeneralIds>
    <StringID>61</StringID>
  </GeneralIds>
  <GeneralIds>
    <StringID>62</StringID>
  </GeneralIds>
  <GeneralIds>
    <StringID>63</StringID>
  </GeneralIds>
  <GeneralIds>
    <StringID>64</StringID>
  </GeneralIds>
  <GeneralIds>
    <StringID>65</StringID>
  </GeneralIds>
  <GeneralIds>
    <StringID>66</StringID>
  </GeneralIds>
  <GeneralIds>
    <StringID>67</StringID>
  </GeneralIds>
  <GeneralIds>
    <StringID>68</StringID>
  </GeneralIds>
  <GeneralIds>
    <StringID>69</StringID>
  </GeneralIds>
  <GeneralIds>
    <StringID>70</StringID>
  </GeneralIds>
  <GeneralIds>
    <StringID>71</StringID>
  </GeneralIds>
  <GeneralIds>
    <StringID>72</StringID>
  </GeneralIds>
  <GeneralIds>
    <StringID>73</StringID>
  </GeneralIds>
  <GeneralIds>
    <StringID>74</StringID>
  </GeneralIds>
  <GeneralIds>
    <StringID>75</StringID>
  </GeneralIds>
  <GeneralIds>
    <StringID>76</StringID>
  </GeneralIds>
  <GeneralIds>
    <StringID>77</StringID>
  </GeneralIds>
  <GeneralIds>
    <StringID>78</StringID>
  </GeneralIds>
  <GeneralIds>
    <StringID>79</StringID>
  </GeneralIds>
  <GeneralIds>
    <StringID>80</StringID>
  </GeneralIds>
  <GeneralIds>
    <StringID>81</StringID>
  </GeneralIds>
  <GeneralIds>
    <StringID>82</StringID>
  </GeneralIds>
  <GeneralIds>
    <StringID>83</StringID>
  </GeneralIds>
  <GeneralIds>
    <StringID>84</StringID>
  </GeneralIds>
  <GeneralIds>
    <StringID>85</StringID>
  </GeneralIds>
  <GeneralIds>
    <StringID>86</StringID>
  </GeneralIds>
  <GeneralIds>
    <StringID>87</StringID>
  </GeneralIds>
  <GeneralIds>
    <StringID>88</StringID>
  </GeneralIds>
  <GeneralIds>
    <StringID>89</StringID>
  </GeneralIds>
  <GeneralIds>
    <StringID>90</StringID>
  </GeneralIds>
  <GeneralIds>
    <StringID>91</StringID>
  </GeneralIds>
  <GeneralIds>
    <StringID>92</StringID>
  </GeneralIds>
  <GeneralIds>
    <StringID>93</StringID>
  </GeneralIds>
  <GeneralIds>
    <StringID>94</StringID>
    <Comment>Previous text: Популяційний метод</Comment>
  </GeneralIds>
  <GeneralIds>
    <StringID>95</StringID>
    <Comment>Previous text: Розрахувати</Comment>
  </GeneralIds>
  <GeneralIds>
    <StringID>96</StringID>
    <Comment>Previous text: Закрити</Comment>
  </GeneralIds>
  <GeneralIds>
    <StringID>97</StringID>
  </GeneralIds>
  <GeneralIds>
    <StringID>98</StringID>
  </GeneralIds>
  <GeneralIds>
    <StringID>99</StringID>
  </GeneralIds>
  <GeneralIds>
    <StringID>100</StringID>
  </GeneralIds>
  <GeneralIds>
    <StringID>101</StringID>
  </GeneralIds>
  <GeneralIds>
    <StringID>102</StringID>
  </GeneralIds>
  <GeneralIds>
    <StringID>103</StringID>
  </GeneralIds>
  <GeneralIds>
    <StringID>104</StringID>
  </GeneralIds>
  <GeneralIds>
    <StringID>105</StringID>
  </GeneralIds>
  <GeneralIds>
    <StringID>106</StringID>
  </GeneralIds>
  <GeneralIds>
    <StringID>107</StringID>
  </GeneralIds>
  <GeneralIds>
    <StringID>108</StringID>
  </GeneralIds>
  <GeneralIds>
    <StringID>109</StringID>
  </GeneralIds>
  <GeneralIds>
    <StringID>110</StringID>
  </GeneralIds>
  <GeneralIds>
    <StringID>111</StringID>
  </GeneralIds>
  <GeneralIds>
    <StringID>112</StringID>
  </GeneralIds>
  <GeneralIds>
    <StringID>113</StringID>
  </GeneralIds>
  <GeneralIds>
    <StringID>114</StringID>
  </GeneralIds>
  <GeneralIds>
    <StringID>115</StringID>
  </GeneralIds>
  <GeneralIds>
    <StringID>116</StringID>
  </GeneralIds>
  <GeneralIds>
    <StringID>117</StringID>
  </GeneralIds>
  <GeneralIds>
    <StringID>118</StringID>
    <Comment>Previous text: Close</Comment>
  </GeneralIds>
  <GeneralIds>
    <StringID>119</StringID>
    <Comment>Previous text: Таблиця 2</Comment>
  </GeneralIds>
  <GeneralIds>
    <StringID>120</StringID>
    <Comment>Previous text: Таблиця 23</Comment>
  </GeneralIds>
  <GeneralIds>
    <StringID>121</StringID>
    <Comment>Previous text: Таблиця 24</Comment>
  </GeneralIds>
  <Languages>
    <LanguageID>9</LanguageID>
    <LanguageName>English</LanguageName>
    <IetfLanguageTag>en</IetfLanguageTag>
    <ColumnNumber>0</ColumnNumber>
  </Languages>
  <Languages>
    <LanguageID>34</LanguageID>
    <LanguageName>Ukrainian</LanguageName>
    <IetfLanguageTag>uk</IetfLanguageTag>
    <ColumnNumber>1</ColumnNumber>
  </Languages>
  <Languages>
    <LanguageID>1049</LanguageID>
    <LanguageName>Russian (Russia)</LanguageName>
    <IetfLanguageTag>ru-RU</IetfLanguageTag>
    <ColumnNumber>2</ColumnNumber>
  </Languages>
  <GeneralTexts>
    <StringID>1</StringID>
    <LanguageID>9</LanguageID>
    <LanguageText>AboutBox1</LanguageText>
    <Status>1</Status>
  </GeneralTexts>
  <GeneralTexts>
    <StringID>2</StringID>
    <LanguageID>9</LanguageID>
    <LanguageText>Product Name</LanguageText>
    <Status>1</Status>
  </GeneralTexts>
  <GeneralTexts>
    <StringID>3</StringID>
    <LanguageID>9</LanguageID>
    <LanguageText>Version</LanguageText>
    <Status>1</Status>
  </GeneralTexts>
  <GeneralTexts>
    <StringID>4</StringID>
    <LanguageID>9</LanguageID>
    <LanguageText>Copyright</LanguageText>
    <Status>1</Status>
  </GeneralTexts>
  <GeneralTexts>
    <StringID>5</StringID>
    <LanguageID>9</LanguageID>
    <LanguageText>Company Name</LanguageText>
    <Status>1</Status>
  </GeneralTexts>
  <GeneralTexts>
    <StringID>6</StringID>
    <LanguageID>9</LanguageID>
    <LanguageText>Description</LanguageText>
    <Status>1</Status>
  </GeneralTexts>
  <GeneralTexts>
    <StringID>7</StringID>
    <LanguageID>9</LanguageID>
    <LanguageText>&amp;OK</LanguageText>
    <Status>1</Status>
  </GeneralTexts>
  <GeneralTexts>
    <StringID>8</StringID>
    <LanguageID>9</LanguageID>
    <LanguageText>Популяційний метод</LanguageText>
    <Status>1</Status>
  </GeneralTexts>
  <GeneralTexts>
    <StringID>9</StringID>
    <LanguageID>9</LanguageID>
    <LanguageText>Розрахувати</LanguageText>
    <Status>1</Status>
  </GeneralTexts>
  <GeneralTexts>
    <StringID>10</StringID>
    <LanguageID>9</LanguageID>
    <LanguageText>Закрити</LanguageText>
    <Status>1</Status>
  </GeneralTexts>
  <GeneralTexts>
    <StringID>11</StringID>
    <LanguageID>9</LanguageID>
    <LanguageText>Назва дослідження</LanguageText>
    <Status>1</Status>
  </GeneralTexts>
  <GeneralTexts>
    <StringID>12</StringID>
    <LanguageID>9</LanguageID>
    <LanguageText>Дата</LanguageText>
    <Status>1</Status>
  </GeneralTexts>
  <GeneralTexts>
    <StringID>13</StringID>
    <LanguageID>9</LanguageID>
    <LanguageText>Кількість
хворих</LanguageText>
    <Status>1</Status>
  </GeneralTexts>
  <GeneralTexts>
    <StringID>14</StringID>
    <LanguageID>9</LanguageID>
    <LanguageText>Схильні до шкідливого
впливу</LanguageText>
    <Status>1</Status>
  </GeneralTexts>
  <GeneralTexts>
    <StringID>15</StringID>
    <LanguageID>9</LanguageID>
    <LanguageText>Не схильних до
шкідливому впливу</LanguageText>
    <Status>1</Status>
  </GeneralTexts>
  <GeneralTexts>
    <StringID>16</StringID>
    <LanguageID>9</LanguageID>
    <LanguageText>Рівень на 1000</LanguageText>
    <Status>1</Status>
  </GeneralTexts>
  <GeneralTexts>
    <StringID>17</StringID>
    <LanguageID>9</LanguageID>
    <LanguageText>Людино
років</LanguageText>
    <Status>1</Status>
  </GeneralTexts>
  <GeneralTexts>
    <StringID>18</StringID>
    <LanguageID>9</LanguageID>
    <LanguageText>Еталонна
модель</LanguageText>
    <Status>1</Status>
  </GeneralTexts>
  <GeneralTexts>
    <StringID>19</StringID>
    <LanguageID>9</LanguageID>
    <LanguageText>Головне управління</LanguageText>
    <Status>1</Status>
  </GeneralTexts>
  <GeneralTexts>
    <StringID>20</StringID>
    <LanguageID>9</LanguageID>
    <LanguageText>Досліджувана
модель</LanguageText>
    <Status>1</Status>
  </GeneralTexts>
  <GeneralTexts>
    <StringID>21</StringID>
    <LanguageID>9</LanguageID>
    <LanguageText>Доменний цех</LanguageText>
    <Status>1</Status>
  </GeneralTexts>
  <GeneralTexts>
    <StringID>22</StringID>
    <LanguageID>9</LanguageID>
    <LanguageText>0</LanguageText>
    <Status>1</Status>
  </GeneralTexts>
  <GeneralTexts>
    <StringID>23</StringID>
    <LanguageID>9</LanguageID>
    <LanguageText>Усього</LanguageText>
    <Status>1</Status>
  </GeneralTexts>
  <GeneralTexts>
    <StringID>24</StringID>
    <LanguageID>9</LanguageID>
    <LanguageText>Звіт</LanguageText>
    <Status>1</Status>
  </GeneralTexts>
  <GeneralTexts>
    <StringID>25</StringID>
    <LanguageID>9</LanguageID>
    <LanguageText>Расчет индекса проф. риска</LanguageText>
    <Status>1</Status>
  </GeneralTexts>
  <GeneralTexts>
    <StringID>26</StringID>
    <LanguageID>9</LanguageID>
    <LanguageText>Расчет индекса проф. заболения</LanguageText>
    <Status>1</Status>
  </GeneralTexts>
  <GeneralTexts>
    <StringID>27</StringID>
    <LanguageID>9</LanguageID>
    <LanguageText>Отчет</LanguageText>
    <Status>1</Status>
  </GeneralTexts>
  <GeneralTexts>
    <StringID>28</StringID>
    <LanguageID>9</LanguageID>
    <LanguageText>Оцінка ризиків</LanguageText>
    <Status>1</Status>
  </GeneralTexts>
  <GeneralTexts>
    <StringID>29</StringID>
    <LanguageID>9</LanguageID>
    <LanguageText>PM</LanguageText>
    <Status>1</Status>
  </GeneralTexts>
  <GeneralTexts>
    <StringID>30</StringID>
    <LanguageID>9</LanguageID>
    <LanguageText>RIPR</LanguageText>
    <Status>1</Status>
  </GeneralTexts>
  <GeneralTexts>
    <StringID>31</StringID>
    <LanguageID>9</LanguageID>
    <LanguageText>RIPZ</LanguageText>
    <Status>1</Status>
  </GeneralTexts>
  <GeneralTexts>
    <StringID>32</StringID>
    <LanguageID>9</LanguageID>
    <LanguageText>&amp;New</LanguageText>
    <Status>1</Status>
  </GeneralTexts>
  <GeneralTexts>
    <StringID>33</StringID>
    <LanguageID>9</LanguageID>
    <LanguageText>&amp;Open</LanguageText>
    <Status>1</Status>
  </GeneralTexts>
  <GeneralTexts>
    <StringID>34</StringID>
    <LanguageID>9</LanguageID>
    <LanguageText>&amp;Save</LanguageText>
    <Status>1</Status>
  </GeneralTexts>
  <GeneralTexts>
    <StringID>35</StringID>
    <LanguageID>9</LanguageID>
    <LanguageText>Save &amp;As</LanguageText>
    <Status>1</Status>
  </GeneralTexts>
  <GeneralTexts>
    <StringID>36</StringID>
    <LanguageID>9</LanguageID>
    <LanguageText>&amp;Print</LanguageText>
    <Status>1</Status>
  </GeneralTexts>
  <GeneralTexts>
    <StringID>37</StringID>
    <LanguageID>9</LanguageID>
    <LanguageText>Print Pre&amp;view</LanguageText>
    <Status>1</Status>
  </GeneralTexts>
  <GeneralTexts>
    <StringID>38</StringID>
    <LanguageID>9</LanguageID>
    <LanguageText>Print Setup</LanguageText>
    <Status>1</Status>
  </GeneralTexts>
  <GeneralTexts>
    <StringID>39</StringID>
    <LanguageID>9</LanguageID>
    <LanguageText>E&amp;xit</LanguageText>
    <Status>1</Status>
  </GeneralTexts>
  <GeneralTexts>
    <StringID>40</StringID>
    <LanguageID>9</LanguageID>
    <LanguageText>&amp;File</LanguageText>
    <Status>1</Status>
  </GeneralTexts>
  <GeneralTexts>
    <StringID>41</StringID>
    <LanguageID>9</LanguageID>
    <LanguageText>&amp;Undo</LanguageText>
    <Status>1</Status>
  </GeneralTexts>
  <GeneralTexts>
    <StringID>42</StringID>
    <LanguageID>9</LanguageID>
    <LanguageText>&amp;Redo</LanguageText>
    <Status>1</Status>
  </GeneralTexts>
  <GeneralTexts>
    <StringID>43</StringID>
    <LanguageID>9</LanguageID>
    <LanguageText>Cu&amp;t</LanguageText>
    <Status>1</Status>
  </GeneralTexts>
  <GeneralTexts>
    <StringID>44</StringID>
    <LanguageID>9</LanguageID>
    <LanguageText>&amp;Copy</LanguageText>
    <Status>1</Status>
  </GeneralTexts>
  <GeneralTexts>
    <StringID>45</StringID>
    <LanguageID>9</LanguageID>
    <LanguageText>&amp;Paste</LanguageText>
    <Status>1</Status>
  </GeneralTexts>
  <GeneralTexts>
    <StringID>46</StringID>
    <LanguageID>9</LanguageID>
    <LanguageText>Select &amp;All</LanguageText>
    <Status>1</Status>
  </GeneralTexts>
  <GeneralTexts>
    <StringID>47</StringID>
    <LanguageID>9</LanguageID>
    <LanguageText>&amp;Edit</LanguageText>
    <Status>1</Status>
  </GeneralTexts>
  <GeneralTexts>
    <StringID>48</StringID>
    <LanguageID>9</LanguageID>
    <LanguageText>&amp;Toolbar</LanguageText>
    <Status>1</Status>
  </GeneralTexts>
  <GeneralTexts>
    <StringID>49</StringID>
    <LanguageID>9</LanguageID>
    <LanguageText>&amp;Status Bar</LanguageText>
    <Status>1</Status>
  </GeneralTexts>
  <GeneralTexts>
    <StringID>50</StringID>
    <LanguageID>9</LanguageID>
    <LanguageText>&amp;View</LanguageText>
    <Status>1</Status>
  </GeneralTexts>
  <GeneralTexts>
    <StringID>51</StringID>
    <LanguageID>9</LanguageID>
    <LanguageText>&amp;Options</LanguageText>
    <Status>1</Status>
  </GeneralTexts>
  <GeneralTexts>
    <StringID>52</StringID>
    <LanguageID>9</LanguageID>
    <LanguageText>&amp;Tools</LanguageText>
    <Status>1</Status>
  </GeneralTexts>
  <GeneralTexts>
    <StringID>53</StringID>
    <LanguageID>9</LanguageID>
    <LanguageText>&amp;New Window</LanguageText>
    <Status>1</Status>
  </GeneralTexts>
  <GeneralTexts>
    <StringID>54</StringID>
    <LanguageID>9</LanguageID>
    <LanguageText>&amp;Cascade</LanguageText>
    <Status>1</Status>
  </GeneralTexts>
  <GeneralTexts>
    <StringID>55</StringID>
    <LanguageID>9</LanguageID>
    <LanguageText>Tile &amp;Vertical</LanguageText>
    <Status>1</Status>
  </GeneralTexts>
  <GeneralTexts>
    <StringID>56</StringID>
    <LanguageID>9</LanguageID>
    <LanguageText>Tile &amp;Horizontal</LanguageText>
    <Status>1</Status>
  </GeneralTexts>
  <GeneralTexts>
    <StringID>57</StringID>
    <LanguageID>9</LanguageID>
    <LanguageText>C&amp;lose All</LanguageText>
    <Status>1</Status>
  </GeneralTexts>
  <GeneralTexts>
    <StringID>58</StringID>
    <LanguageID>9</LanguageID>
    <LanguageText>&amp;Arrange Icons</LanguageText>
    <Status>1</Status>
  </GeneralTexts>
  <GeneralTexts>
    <StringID>59</StringID>
    <LanguageID>9</LanguageID>
    <LanguageText>&amp;Windows</LanguageText>
    <Status>1</Status>
  </GeneralTexts>
  <GeneralTexts>
    <StringID>60</StringID>
    <LanguageID>9</LanguageID>
    <LanguageText>Таблиця 2</LanguageText>
    <Status>1</Status>
  </GeneralTexts>
  <GeneralTexts>
    <StringID>61</StringID>
    <LanguageID>9</LanguageID>
    <LanguageText>Таблиця 23</LanguageText>
    <Status>1</Status>
  </GeneralTexts>
  <GeneralTexts>
    <StringID>62</StringID>
    <LanguageID>9</LanguageID>
    <LanguageText>Таблиця 24</LanguageText>
    <Status>1</Status>
  </GeneralTexts>
  <GeneralTexts>
    <StringID>63</StringID>
    <LanguageID>9</LanguageID>
    <LanguageText>Довідник</LanguageText>
    <Status>1</Status>
  </GeneralTexts>
  <GeneralTexts>
    <StringID>64</StringID>
    <LanguageID>9</LanguageID>
    <LanguageText>&amp;Contents</LanguageText>
    <Status>1</Status>
  </GeneralTexts>
  <GeneralTexts>
    <StringID>65</StringID>
    <LanguageID>9</LanguageID>
    <LanguageText>&amp;Index</LanguageText>
    <Status>1</Status>
  </GeneralTexts>
  <GeneralTexts>
    <StringID>66</StringID>
    <LanguageID>9</LanguageID>
    <LanguageText>&amp;Search</LanguageText>
    <Status>1</Status>
  </GeneralTexts>
  <GeneralTexts>
    <StringID>67</StringID>
    <LanguageID>9</LanguageID>
    <LanguageText>&amp;About ... ...</LanguageText>
    <Status>1</Status>
  </GeneralTexts>
  <GeneralTexts>
    <StringID>68</StringID>
    <LanguageID>9</LanguageID>
    <LanguageText>&amp;Help</LanguageText>
    <Status>1</Status>
  </GeneralTexts>
  <GeneralTexts>
    <StringID>69</StringID>
    <LanguageID>9</LanguageID>
    <LanguageText>MenuStrip</LanguageText>
    <Status>1</Status>
  </GeneralTexts>
  <GeneralTexts>
    <StringID>70</StringID>
    <LanguageID>9</LanguageID>
    <LanguageText>New</LanguageText>
    <Status>1</Status>
  </GeneralTexts>
  <GeneralTexts>
    <StringID>71</StringID>
    <LanguageID>9</LanguageID>
    <LanguageText>Open</LanguageText>
    <Status>1</Status>
  </GeneralTexts>
  <GeneralTexts>
    <StringID>72</StringID>
    <LanguageID>9</LanguageID>
    <LanguageText>Save</LanguageText>
    <Status>1</Status>
  </GeneralTexts>
  <GeneralTexts>
    <StringID>73</StringID>
    <LanguageID>9</LanguageID>
    <LanguageText>Print</LanguageText>
    <Status>1</Status>
  </GeneralTexts>
  <GeneralTexts>
    <StringID>74</StringID>
    <LanguageID>9</LanguageID>
    <LanguageText>Print Preview</LanguageText>
    <Status>1</Status>
  </GeneralTexts>
  <GeneralTexts>
    <StringID>75</StringID>
    <LanguageID>9</LanguageID>
    <LanguageText>Help</LanguageText>
    <Status>1</Status>
  </GeneralTexts>
  <GeneralTexts>
    <StringID>76</StringID>
    <LanguageID>9</LanguageID>
    <LanguageText>ToolStrip</LanguageText>
    <Status>1</Status>
  </GeneralTexts>
  <GeneralTexts>
    <StringID>77</StringID>
    <LanguageID>9</LanguageID>
    <LanguageText>Status</LanguageText>
    <Status>1</Status>
  </GeneralTexts>
  <GeneralTexts>
    <StringID>78</StringID>
    <LanguageID>9</LanguageID>
    <LanguageText>StatusStrip</LanguageText>
    <Status>1</Status>
  </GeneralTexts>
  <GeneralTexts>
    <StringID>79</StringID>
    <LanguageID>9</LanguageID>
    <LanguageText>About {0}</LanguageText>
    <Status>1</Status>
  </GeneralTexts>
  <GeneralTexts>
    <StringID>80</StringID>
    <LanguageID>9</LanguageID>
    <LanguageText>Version {0}</LanguageText>
    <Status>1</Status>
  </GeneralTexts>
  <GeneralTexts>
    <StringID>81</StringID>
    <LanguageID>9</LanguageID>
    <LanguageText>Divide by zero error</LanguageText>
    <Status>1</Status>
  </GeneralTexts>
  <GeneralTexts>
    <StringID>82</StringID>
    <LanguageID>9</LanguageID>
    <LanguageText>Название исследования</LanguageText>
    <Status>1</Status>
  </GeneralTexts>
  <GeneralTexts>
    <StringID>83</StringID>
    <LanguageID>9</LanguageID>
    <LanguageText xml:space="preserve"> </LanguageText>
    <Status>1</Status>
  </GeneralTexts>
  <GeneralTexts>
    <StringID>84</StringID>
    <LanguageID>9</LanguageID>
    <LanguageText>Исследуемая модель</LanguageText>
    <Status>1</Status>
  </GeneralTexts>
  <GeneralTexts>
    <StringID>85</StringID>
    <LanguageID>9</LanguageID>
    <LanguageText>Эталонная модель</LanguageText>
    <Status>1</Status>
  </GeneralTexts>
  <GeneralTexts>
    <StringID>86</StringID>
    <LanguageID>9</LanguageID>
    <LanguageText>Подвер. вредному воздействию, кол-во заб.</LanguageText>
    <Status>1</Status>
  </GeneralTexts>
  <GeneralTexts>
    <StringID>87</StringID>
    <LanguageID>9</LanguageID>
    <LanguageText>Подвер. вредному воздействию, чел. лет</LanguageText>
    <Status>1</Status>
  </GeneralTexts>
  <GeneralTexts>
    <StringID>88</StringID>
    <LanguageID>9</LanguageID>
    <LanguageText>Не подвергавшиеся вредному воздействию</LanguageText>
    <Status>1</Status>
  </GeneralTexts>
  <GeneralTexts>
    <StringID>89</StringID>
    <LanguageID>9</LanguageID>
    <LanguageText>Всего Подвер. вредному воздействию</LanguageText>
    <Status>1</Status>
  </GeneralTexts>
  <GeneralTexts>
    <StringID>90</StringID>
    <LanguageID>9</LanguageID>
    <LanguageText>Всего Не Подвер. вредному воздействию</LanguageText>
    <Status>1</Status>
  </GeneralTexts>
  <GeneralTexts>
    <StringID>91</StringID>
    <LanguageID>9</LanguageID>
    <LanguageText>Уровень на 1000 </LanguageText>
    <Status>1</Status>
  </GeneralTexts>
  <GeneralTexts>
    <StringID>92</StringID>
    <LanguageID>9</LanguageID>
    <LanguageText>Уровень на 1000 лет</LanguageText>
    <Status>1</Status>
  </GeneralTexts>
  <GeneralTexts>
    <StringID>93</StringID>
    <LanguageID>9</LanguageID>
    <LanguageText>Text Files (*.txt)|*.txt|All Files (*.*)|*.*</LanguageText>
    <Status>1</Status>
  </GeneralTexts>
  <GeneralTexts>
    <StringID>7</StringID>
    <LanguageID>1049</LanguageID>
    <LanguageText>ОК</LanguageText>
    <Status>3</Status>
  </GeneralTexts>
  <GeneralTexts>
    <StringID>44</StringID>
    <LanguageID>1049</LanguageID>
    <LanguageText>Копировать</LanguageText>
    <Status>3</Status>
  </GeneralTexts>
  <GeneralTexts>
    <StringID>43</StringID>
    <LanguageID>1049</LanguageID>
    <LanguageText>Вырезать</LanguageText>
    <Status>3</Status>
  </GeneralTexts>
  <GeneralTexts>
    <StringID>47</StringID>
    <LanguageID>1049</LanguageID>
    <LanguageText>Правка или Изменить</LanguageText>
    <Status>3</Status>
  </GeneralTexts>
  <GeneralTexts>
    <StringID>39</StringID>
    <LanguageID>1049</LanguageID>
    <LanguageText>Выход</LanguageText>
    <Status>3</Status>
  </GeneralTexts>
  <GeneralTexts>
    <StringID>40</StringID>
    <LanguageID>1049</LanguageID>
    <LanguageText>файл</LanguageText>
    <Status>3</Status>
  </GeneralTexts>
  <GeneralTexts>
    <StringID>68</StringID>
    <LanguageID>1049</LanguageID>
    <LanguageText>Справка</LanguageText>
    <Status>3</Status>
  </GeneralTexts>
  <GeneralTexts>
    <StringID>75</StringID>
    <LanguageID>1049</LanguageID>
    <LanguageText>Справка</LanguageText>
    <Status>3</Status>
  </GeneralTexts>
  <GeneralTexts>
    <StringID>70</StringID>
    <LanguageID>1049</LanguageID>
    <LanguageText>Создать</LanguageText>
    <Status>3</Status>
  </GeneralTexts>
  <GeneralTexts>
    <StringID>32</StringID>
    <LanguageID>1049</LanguageID>
    <LanguageText>Создать</LanguageText>
    <Status>3</Status>
  </GeneralTexts>
  <GeneralTexts>
    <StringID>71</StringID>
    <LanguageID>1049</LanguageID>
    <LanguageText>Открыть</LanguageText>
    <Status>3</Status>
  </GeneralTexts>
  <GeneralTexts>
    <StringID>33</StringID>
    <LanguageID>1049</LanguageID>
    <LanguageText>Открыть</LanguageText>
    <Status>3</Status>
  </GeneralTexts>
  <GeneralTexts>
    <StringID>51</StringID>
    <LanguageID>1049</LanguageID>
    <LanguageText>Параметры</LanguageText>
    <Status>3</Status>
  </GeneralTexts>
  <GeneralTexts>
    <StringID>45</StringID>
    <LanguageID>1049</LanguageID>
    <LanguageText>Вставить или Вставка</LanguageText>
    <Status>3</Status>
  </GeneralTexts>
  <GeneralTexts>
    <StringID>73</StringID>
    <LanguageID>1049</LanguageID>
    <LanguageText>Печать</LanguageText>
    <Status>3</Status>
  </GeneralTexts>
  <GeneralTexts>
    <StringID>36</StringID>
    <LanguageID>1049</LanguageID>
    <LanguageText>Печать</LanguageText>
    <Status>3</Status>
  </GeneralTexts>
  <GeneralTexts>
    <StringID>42</StringID>
    <LanguageID>1049</LanguageID>
    <LanguageText>Вернуть</LanguageText>
    <Status>3</Status>
  </GeneralTexts>
  <GeneralTexts>
    <StringID>35</StringID>
    <LanguageID>1049</LanguageID>
    <LanguageText>Сохранить как</LanguageText>
    <Status>3</Status>
  </GeneralTexts>
  <GeneralTexts>
    <StringID>72</StringID>
    <LanguageID>1049</LanguageID>
    <LanguageText>Сохранить</LanguageText>
    <Status>3</Status>
  </GeneralTexts>
  <GeneralTexts>
    <StringID>34</StringID>
    <LanguageID>1049</LanguageID>
    <LanguageText>Сохранить</LanguageText>
    <Status>3</Status>
  </GeneralTexts>
  <GeneralTexts>
    <StringID>66</StringID>
    <LanguageID>1049</LanguageID>
    <LanguageText>Найти</LanguageText>
    <Status>3</Status>
  </GeneralTexts>
  <GeneralTexts>
    <StringID>46</StringID>
    <LanguageID>1049</LanguageID>
    <LanguageText>выделить все</LanguageText>
    <Status>3</Status>
  </GeneralTexts>
  <GeneralTexts>
    <StringID>48</StringID>
    <LanguageID>1049</LanguageID>
    <LanguageText>панель инструментов</LanguageText>
    <Status>3</Status>
  </GeneralTexts>
  <GeneralTexts>
    <StringID>41</StringID>
    <LanguageID>1049</LanguageID>
    <LanguageText>Отменить</LanguageText>
    <Status>3</Status>
  </GeneralTexts>
  <GeneralTexts>
    <StringID>94</StringID>
    <LanguageID>9</LanguageID>
    <LanguageText>Population method</LanguageText>
    <Status>2</Status>
  </GeneralTexts>
  <GeneralTexts>
    <StringID>94</StringID>
    <LanguageID>1049</LanguageID>
    <LanguageText>Популяционий метод</LanguageText>
    <Status>7</Status>
  </GeneralTexts>
  <GeneralTexts>
    <StringID>95</StringID>
    <LanguageID>9</LanguageID>
    <LanguageText>Calculate</LanguageText>
    <Status>2</Status>
  </GeneralTexts>
  <GeneralTexts>
    <StringID>95</StringID>
    <LanguageID>1049</LanguageID>
    <LanguageText>Рассчитать</LanguageText>
    <Status>7</Status>
  </GeneralTexts>
  <GeneralTexts>
    <StringID>96</StringID>
    <LanguageID>9</LanguageID>
    <LanguageText>Close</LanguageText>
    <Status>2</Status>
  </GeneralTexts>
  <GeneralTexts>
    <StringID>96</StringID>
    <LanguageID>1049</LanguageID>
    <LanguageText>Закрыть</LanguageText>
    <Status>7</Status>
  </GeneralTexts>
  <GeneralTexts>
    <StringID>94</StringID>
    <LanguageID>34</LanguageID>
    <LanguageText>Популяційний метод</LanguageText>
    <Status>2</Status>
  </GeneralTexts>
  <GeneralTexts>
    <StringID>97</StringID>
    <LanguageID>9</LanguageID>
    <LanguageText>key :</LanguageText>
    <Status>1</Status>
  </GeneralTexts>
  <GeneralTexts>
    <StringID>98</StringID>
    <LanguageID>9</LanguageID>
    <LanguageText>kpr:</LanguageText>
    <Status>1</Status>
  </GeneralTexts>
  <GeneralTexts>
    <StringID>99</StringID>
    <LanguageID>9</LanguageID>
    <LanguageText>kup:</LanguageText>
    <Status>1</Status>
  </GeneralTexts>
  <GeneralTexts>
    <StringID>100</StringID>
    <LanguageID>9</LanguageID>
    <LanguageText>termin:</LanguageText>
    <Status>1</Status>
  </GeneralTexts>
  <GeneralTexts>
    <StringID>101</StringID>
    <LanguageID>9</LanguageID>
    <LanguageText>index n:</LanguageText>
    <Status>1</Status>
  </GeneralTexts>
  <GeneralTexts>
    <StringID>102</StringID>
    <LanguageID>9</LanguageID>
    <LanguageText>index v:</LanguageText>
    <Status>1</Status>
  </GeneralTexts>
  <GeneralTexts>
    <StringID>103</StringID>
    <LanguageID>9</LanguageID>
    <LanguageText>Add new</LanguageText>
    <Status>1</Status>
  </GeneralTexts>
  <GeneralTexts>
    <StringID>104</StringID>
    <LanguageID>9</LanguageID>
    <LanguageText>of {0}</LanguageText>
    <Status>1</Status>
  </GeneralTexts>
  <GeneralTexts>
    <StringID>105</StringID>
    <LanguageID>9</LanguageID>
    <LanguageText>Total number of items</LanguageText>
    <Status>1</Status>
  </GeneralTexts>
  <GeneralTexts>
    <StringID>106</StringID>
    <LanguageID>9</LanguageID>
    <LanguageText>Delete</LanguageText>
    <Status>1</Status>
  </GeneralTexts>
  <GeneralTexts>
    <StringID>107</StringID>
    <LanguageID>9</LanguageID>
    <LanguageText>Move first</LanguageText>
    <Status>1</Status>
  </GeneralTexts>
  <GeneralTexts>
    <StringID>108</StringID>
    <LanguageID>9</LanguageID>
    <LanguageText>Move previous</LanguageText>
    <Status>1</Status>
  </GeneralTexts>
  <GeneralTexts>
    <StringID>109</StringID>
    <LanguageID>9</LanguageID>
    <LanguageText>Position</LanguageText>
    <Status>1</Status>
  </GeneralTexts>
  <GeneralTexts>
    <StringID>110</StringID>
    <LanguageID>9</LanguageID>
    <LanguageText>Current position</LanguageText>
    <Status>1</Status>
  </GeneralTexts>
  <GeneralTexts>
    <StringID>111</StringID>
    <LanguageID>9</LanguageID>
    <LanguageText>Move next</LanguageText>
    <Status>1</Status>
  </GeneralTexts>
  <GeneralTexts>
    <StringID>112</StringID>
    <LanguageID>9</LanguageID>
    <LanguageText>Move last</LanguageText>
    <Status>1</Status>
  </GeneralTexts>
  <GeneralTexts>
    <StringID>113</StringID>
    <LanguageID>9</LanguageID>
    <LanguageText>Save Data</LanguageText>
    <Status>1</Status>
  </GeneralTexts>
  <GeneralTexts>
    <StringID>114</StringID>
    <LanguageID>9</LanguageID>
    <LanguageText>bindingNavigator1</LanguageText>
    <Status>1</Status>
  </GeneralTexts>
  <GeneralTexts>
    <StringID>115</StringID>
    <LanguageID>9</LanguageID>
    <LanguageText>Form6</LanguageText>
    <Status>1</Status>
  </GeneralTexts>
  <GeneralTexts>
    <StringID>116</StringID>
    <LanguageID>9</LanguageID>
    <LanguageText>Form7</LanguageText>
    <Status>1</Status>
  </GeneralTexts>
  <GeneralTexts>
    <StringID>117</StringID>
    <LanguageID>9</LanguageID>
    <LanguageText>Form8</LanguageText>
    <Status>1</Status>
  </GeneralTexts>
  <GeneralTexts>
    <StringID>118</StringID>
    <LanguageID>9</LanguageID>
    <LanguageText>Закрити</LanguageText>
    <Status>1</Status>
  </GeneralTexts>
  <GeneralTexts>
    <StringID>118</StringID>
    <LanguageID>1049</LanguageID>
    <LanguageText>Закрыть</LanguageText>
    <Status>7</Status>
  </GeneralTexts>
  <GeneralTexts>
    <StringID>119</StringID>
    <LanguageID>9</LanguageID>
    <LanguageText>tab2</LanguageText>
    <Status>1</Status>
  </GeneralTexts>
  <GeneralTexts>
    <StringID>120</StringID>
    <LanguageID>9</LanguageID>
    <LanguageText>tab23</LanguageText>
    <Status>1</Status>
  </GeneralTexts>
  <GeneralTexts>
    <StringID>121</StringID>
    <LanguageID>9</LanguageID>
    <LanguageText>tab24</LanguageText>
    <Status>1</Status>
  </GeneralTexts>
  <GeneralTexts>
    <StringID>8</StringID>
    <LanguageID>1049</LanguageID>
    <LanguageText>Популяционий метод</LanguageText>
    <Status>3</Status>
  </GeneralTexts>
  <GeneralTexts>
    <StringID>106</StringID>
    <LanguageID>1049</LanguageID>
    <LanguageText>Очистить</LanguageText>
    <Status>3</Status>
  </GeneralTexts>
  <Properties>
    <Component>AboutBox1.cs</Component>
    <Name>AboutBox1.Text</Name>
    <StringID>1</StringID>
    <Selected>true</Selected>
    <ResourceName>$this.Text</ResourceName>
    <Hidden>false</Hidden>
  </Properties>
  <Properties>
    <Component>AboutBox1.cs</Component>
    <Name>labelProductName.Text</Name>
    <StringID>2</StringID>
    <Selected>true</Selected>
    <ResourceName>labelProductName.Text</ResourceName>
    <Hidden>false</Hidden>
  </Properties>
  <Properties>
    <Component>AboutBox1.cs</Component>
    <Name>labelVersion.Text</Name>
    <StringID>3</StringID>
    <Selected>true</Selected>
    <ResourceName>labelVersion.Text</ResourceName>
    <Hidden>false</Hidden>
  </Properties>
  <Properties>
    <Component>AboutBox1.cs</Component>
    <Name>labelCopyright.Text</Name>
    <StringID>4</StringID>
    <Selected>true</Selected>
    <ResourceName>labelCopyright.Text</ResourceName>
    <Hidden>false</Hidden>
  </Properties>
  <Properties>
    <Component>AboutBox1.cs</Component>
    <Name>labelCompanyName.Text</Name>
    <StringID>5</StringID>
    <Selected>true</Selected>
    <ResourceName>labelCompanyName.Text</ResourceName>
    <Hidden>false</Hidden>
  </Properties>
  <Properties>
    <Component>AboutBox1.cs</Component>
    <Name>textBoxDescription.Text</Name>
    <StringID>6</StringID>
    <Selected>true</Selected>
    <ResourceName>textBoxDescription.Text</ResourceName>
    <Hidden>false</Hidden>
  </Properties>
  <Properties>
    <Component>AboutBox1.cs</Component>
    <Name>textBoxDescription.Lines[0]</Name>
    <StringID>6</StringID>
    <Selected>true</Selected>
    <ResourceName>textBoxDescription.Lines[0]</ResourceName>
    <Hidden>false</Hidden>
  </Properties>
  <Properties>
    <Component>AboutBox1.cs</Component>
    <Name>okButton.Text</Name>
    <StringID>7</StringID>
    <Selected>true</Selected>
    <ResourceName>okButton.Text</ResourceName>
    <Hidden>false</Hidden>
  </Properties>
  <Properties>
    <Component>Form1.cs</Component>
    <Name>Form1.Text</Name>
    <StringID>94</StringID>
    <Selected>true</Selected>
    <ResourceName>$this.Text</ResourceName>
    <Hidden>false</Hidden>
  </Properties>
  <Properties>
    <Component>Form1.cs</Component>
    <Name>button1.Text</Name>
    <StringID>95</StringID>
    <Selected>true</Selected>
    <ResourceName>button1.Text</ResourceName>
    <Hidden>false</Hidden>
  </Properties>
  <Properties>
    <Component>Form1.cs</Component>
    <Name>button2.Text</Name>
    <StringID>118</StringID>
    <Selected>true</Selected>
    <ResourceName>button2.Text</ResourceName>
    <Hidden>false</Hidden>
  </Properties>
  <Properties>
    <Component>Form1.cs</Component>
    <Name>label1.Text</Name>
    <StringID>11</StringID>
    <Selected>true</Selected>
    <ResourceName>label1.Text</ResourceName>
    <Hidden>false</Hidden>
  </Properties>
  <Properties>
    <Component>Form1.cs</Component>
    <Name>label2.Text</Name>
    <StringID>12</StringID>
    <Selected>true</Selected>
    <ResourceName>label2.Text</ResourceName>
    <Hidden>false</Hidden>
  </Properties>
  <Properties>
    <Component>Form1.cs</Component>
    <Name>label3.Text</Name>
    <StringID>13</StringID>
    <Selected>true</Selected>
    <ResourceName>label3.Text</ResourceName>
    <Hidden>false</Hidden>
  </Properties>
  <Properties>
    <Component>Form1.cs</Component>
    <Name>label4.Text</Name>
    <StringID>14</StringID>
    <Selected>true</Selected>
    <ResourceName>label4.Text</ResourceName>
    <Hidden>false</Hidden>
  </Properties>
  <Properties>
    <Component>Form1.cs</Component>
    <Name>label5.Text</Name>
    <StringID>15</StringID>
    <Selected>true</Selected>
    <ResourceName>label5.Text</ResourceName>
    <Hidden>false</Hidden>
  </Properties>
  <Properties>
    <Component>Form1.cs</Component>
    <Name>label6.Text</Name>
    <StringID>16</StringID>
    <Selected>true</Selected>
    <ResourceName>label6.Text</ResourceName>
    <Hidden>false</Hidden>
  </Properties>
  <Properties>
    <Component>Form1.cs</Component>
    <Name>label7.Text</Name>
    <StringID>17</StringID>
    <Selected>true</Selected>
    <ResourceName>label7.Text</ResourceName>
    <Hidden>false</Hidden>
  </Properties>
  <Properties>
    <Component>Form1.cs</Component>
    <Name>label8.Text</Name>
    <StringID>18</StringID>
    <Selected>true</Selected>
    <ResourceName>label8.Text</ResourceName>
    <Hidden>false</Hidden>
  </Properties>
  <Properties>
    <Component>Form1.cs</Component>
    <Name>textBox8.Text</Name>
    <StringID>19</StringID>
    <Selected>true</Selected>
    <ResourceName>textBox8.Text</ResourceName>
    <Hidden>false</Hidden>
  </Properties>
  <Properties>
    <Component>Form1.cs</Component>
    <Name>textBox8.Lines[0]</Name>
    <StringID>19</StringID>
    <Selected>true</Selected>
    <ResourceName>textBox8.Lines[0]</ResourceName>
    <Hidden>false</Hidden>
  </Properties>
  <Properties>
    <Component>Form1.cs</Component>
    <Name>label9.Text</Name>
    <StringID>20</StringID>
    <Selected>true</Selected>
    <ResourceName>label9.Text</ResourceName>
    <Hidden>false</Hidden>
  </Properties>
  <Properties>
    <Component>Form1.cs</Component>
    <Name>textBox9.Text</Name>
    <StringID>21</StringID>
    <Selected>true</Selected>
    <ResourceName>textBox9.Text</ResourceName>
    <Hidden>false</Hidden>
  </Properties>
  <Properties>
    <Component>Form1.cs</Component>
    <Name>textBox9.Lines[0]</Name>
    <StringID>21</StringID>
    <Selected>true</Selected>
    <ResourceName>textBox9.Lines[0]</ResourceName>
    <Hidden>false</Hidden>
  </Properties>
  <Properties>
    <Component>Form1.cs</Component>
    <Name>textBox2.Text</Name>
    <Selected>false</Selected>
    <ResourceName>textBox2.Text</ResourceName>
    <Hidden>true</Hidden>
  </Properties>
  <Properties>
    <Component>Form1.cs</Component>
    <Name>textBox2.Lines[0]</Name>
    <Selected>false</Selected>
    <ResourceName>textBox2.Lines[0]</ResourceName>
    <Hidden>true</Hidden>
  </Properties>
  <Properties>
    <Component>Form1.cs</Component>
    <Name>textBox3.Text</Name>
    <Selected>false</Selected>
    <ResourceName>textBox3.Text</ResourceName>
    <Hidden>true</Hidden>
  </Properties>
  <Properties>
    <Component>Form1.cs</Component>
    <Name>textBox3.Lines[0]</Name>
    <Selected>false</Selected>
    <ResourceName>textBox3.Lines[0]</ResourceName>
    <Hidden>true</Hidden>
  </Properties>
  <Properties>
    <Component>Form1.cs</Component>
    <Name>textBox4.Text</Name>
    <Selected>false</Selected>
    <ResourceName>textBox4.Text</ResourceName>
    <Hidden>true</Hidden>
  </Properties>
  <Properties>
    <Component>Form1.cs</Component>
    <Name>textBox4.Lines[0]</Name>
    <Selected>false</Selected>
    <ResourceName>textBox4.Lines[0]</ResourceName>
    <Hidden>true</Hidden>
  </Properties>
  <Properties>
    <Component>Form1.cs</Component>
    <Name>textBox5.Text</Name>
    <Selected>false</Selected>
    <ResourceName>textBox5.Text</ResourceName>
    <Hidden>true</Hidden>
  </Properties>
  <Properties>
    <Component>Form1.cs</Component>
    <Name>textBox5.Lines[0]</Name>
    <Selected>false</Selected>
    <ResourceName>textBox5.Lines[0]</ResourceName>
    <Hidden>true</Hidden>
  </Properties>
  <Properties>
    <Component>Form1.cs</Component>
    <Name>textBox6.Text</Name>
    <Selected>false</Selected>
    <ResourceName>textBox6.Text</ResourceName>
    <Hidden>true</Hidden>
  </Properties>
  <Properties>
    <Component>Form1.cs</Component>
    <Name>textBox6.Lines[0]</Name>
    <Selected>false</Selected>
    <ResourceName>textBox6.Lines[0]</ResourceName>
    <Hidden>true</Hidden>
  </Properties>
  <Properties>
    <Component>Form1.cs</Component>
    <Name>textBox7.Text</Name>
    <Selected>false</Selected>
    <ResourceName>textBox7.Text</ResourceName>
    <Hidden>true</Hidden>
  </Properties>
  <Properties>
    <Component>Form1.cs</Component>
    <Name>textBox7.Lines[0]</Name>
    <Selected>false</Selected>
    <ResourceName>textBox7.Lines[0]</ResourceName>
    <Hidden>true</Hidden>
  </Properties>
  <Properties>
    <Component>Form1.cs</Component>
    <Name>label10.Text</Name>
    <StringID>23</StringID>
    <Selected>true</Selected>
    <ResourceName>label10.Text</ResourceName>
    <Hidden>false</Hidden>
  </Properties>
  <Properties>
    <Component>Form1.cs</Component>
    <Name>textBox10.Text</Name>
    <Selected>false</Selected>
    <ResourceName>textBox10.Text</ResourceName>
    <Hidden>true</Hidden>
  </Properties>
  <Properties>
    <Component>Form1.cs</Component>
    <Name>textBox10.Lines[0]</Name>
    <Selected>false</Selected>
    <ResourceName>textBox10.Lines[0]</ResourceName>
    <Hidden>false</Hidden>
  </Properties>
  <Properties>
    <Component>Form1.cs</Component>
    <Name>textBox11.Text</Name>
    <Selected>false</Selected>
    <ResourceName>textBox11.Text</ResourceName>
    <Hidden>true</Hidden>
  </Properties>
  <Properties>
    <Component>Form1.cs</Component>
    <Name>textBox11.Lines[0]</Name>
    <Selected>false</Selected>
    <ResourceName>textBox11.Lines[0]</ResourceName>
    <Hidden>true</Hidden>
  </Properties>
  <Properties>
    <Component>Form1.cs</Component>
    <Name>button3.Text</Name>
    <StringID>24</StringID>
    <Selected>true</Selected>
    <ResourceName>button3.Text</ResourceName>
    <Hidden>false</Hidden>
  </Properties>
  <Properties>
    <Component>Form2.cs</Component>
    <Name>Form2.Text</Name>
    <StringID>25</StringID>
    <Selected>true</Selected>
    <ResourceName>$this.Text</ResourceName>
    <Hidden>false</Hidden>
  </Properties>
  <Properties>
    <Component>Form3.cs</Component>
    <Name>Form3.Text</Name>
    <StringID>26</StringID>
    <Selected>true</Selected>
    <ResourceName>$this.Text</ResourceName>
    <Hidden>false</Hidden>
  </Properties>
  <Properties>
    <Component>Form5.cs</Component>
    <Name>Form5.Text</Name>
    <StringID>27</StringID>
    <Selected>true</Selected>
    <ResourceName>$this.Text</ResourceName>
    <Hidden>false</Hidden>
  </Properties>
  <Properties>
    <Component>MDIParent1.cs</Component>
    <Name>MDI.Text</Name>
    <StringID>28</StringID>
    <Selected>true</Selected>
    <ResourceName>$this.Text</ResourceName>
    <Hidden>false</Hidden>
  </Properties>
  <Properties>
    <Component>MDIParent1.cs</Component>
    <Name>popMToolStripMenuItem.Text</Name>
    <StringID>29</StringID>
    <Selected>true</Selected>
    <ResourceName>popMToolStripMenuItem.Text</ResourceName>
    <Hidden>false</Hidden>
  </Properties>
  <Properties>
    <Component>MDIParent1.cs</Component>
    <Name>rIPRToolStripMenuItem.Text</Name>
    <StringID>30</StringID>
    <Selected>true</Selected>
    <ResourceName>rIPRToolStripMenuItem.Text</ResourceName>
    <Hidden>false</Hidden>
  </Properties>
  <Properties>
    <Component>MDIParent1.cs</Component>
    <Name>rIPZToolStripMenuItem.Text</Name>
    <StringID>31</StringID>
    <Selected>true</Selected>
    <ResourceName>rIPZToolStripMenuItem.Text</ResourceName>
    <Hidden>false</Hidden>
  </Properties>
  <Properties>
    <Component>MDIParent1.cs</Component>
    <Name>newToolStripMenuItem.Text</Name>
    <StringID>32</StringID>
    <Selected>true</Selected>
    <ResourceName>newToolStripMenuItem.Text</ResourceName>
    <Hidden>false</Hidden>
  </Properties>
  <Properties>
    <Component>MDIParent1.cs</Component>
    <Name>openToolStripMenuItem.Text</Name>
    <StringID>33</StringID>
    <Selected>true</Selected>
    <ResourceName>openToolStripMenuItem.Text</ResourceName>
    <Hidden>false</Hidden>
  </Properties>
  <Properties>
    <Component>MDIParent1.cs</Component>
    <Name>saveToolStripMenuItem.Text</Name>
    <StringID>34</StringID>
    <Selected>true</Selected>
    <ResourceName>saveToolStripMenuItem.Text</ResourceName>
    <Hidden>false</Hidden>
  </Properties>
  <Properties>
    <Component>MDIParent1.cs</Component>
    <Name>saveAsToolStripMenuItem.Text</Name>
    <StringID>35</StringID>
    <Selected>true</Selected>
    <ResourceName>saveAsToolStripMenuItem.Text</ResourceName>
    <Hidden>false</Hidden>
  </Properties>
  <Properties>
    <Component>MDIParent1.cs</Component>
    <Name>printToolStripMenuItem.Text</Name>
    <StringID>36</StringID>
    <Selected>true</Selected>
    <ResourceName>printToolStripMenuItem.Text</ResourceName>
    <Hidden>false</Hidden>
  </Properties>
  <Properties>
    <Component>MDIParent1.cs</Component>
    <Name>printPreviewToolStripMenuItem.Text</Name>
    <StringID>37</StringID>
    <Selected>true</Selected>
    <ResourceName>printPreviewToolStripMenuItem.Text</ResourceName>
    <Hidden>false</Hidden>
  </Properties>
  <Properties>
    <Component>MDIParent1.cs</Component>
    <Name>printSetupToolStripMenuItem.Text</Name>
    <StringID>38</StringID>
    <Selected>true</Selected>
    <ResourceName>printSetupToolStripMenuItem.Text</ResourceName>
    <Hidden>false</Hidden>
  </Properties>
  <Properties>
    <Component>MDIParent1.cs</Component>
    <Name>exitToolStripMenuItem.Text</Name>
    <StringID>39</StringID>
    <Selected>true</Selected>
    <ResourceName>exitToolStripMenuItem.Text</ResourceName>
    <Hidden>false</Hidden>
  </Properties>
  <Properties>
    <Component>MDIParent1.cs</Component>
    <Name>fileMenu.Text</Name>
    <StringID>40</StringID>
    <Selected>true</Selected>
    <ResourceName>fileMenu.Text</ResourceName>
    <Hidden>false</Hidden>
  </Properties>
  <Properties>
    <Component>MDIParent1.cs</Component>
    <Name>undoToolStripMenuItem.Text</Name>
    <StringID>41</StringID>
    <Selected>true</Selected>
    <ResourceName>undoToolStripMenuItem.Text</ResourceName>
    <Hidden>false</Hidden>
  </Properties>
  <Properties>
    <Component>MDIParent1.cs</Component>
    <Name>redoToolStripMenuItem.Text</Name>
    <StringID>42</StringID>
    <Selected>true</Selected>
    <ResourceName>redoToolStripMenuItem.Text</ResourceName>
    <Hidden>false</Hidden>
  </Properties>
  <Properties>
    <Component>MDIParent1.cs</Component>
    <Name>cutToolStripMenuItem.Text</Name>
    <StringID>43</StringID>
    <Selected>true</Selected>
    <ResourceName>cutToolStripMenuItem.Text</ResourceName>
    <Hidden>false</Hidden>
  </Properties>
  <Properties>
    <Component>MDIParent1.cs</Component>
    <Name>copyToolStripMenuItem.Text</Name>
    <StringID>44</StringID>
    <Selected>true</Selected>
    <ResourceName>copyToolStripMenuItem.Text</ResourceName>
    <Hidden>false</Hidden>
  </Properties>
  <Properties>
    <Component>MDIParent1.cs</Component>
    <Name>pasteToolStripMenuItem.Text</Name>
    <StringID>45</StringID>
    <Selected>true</Selected>
    <ResourceName>pasteToolStripMenuItem.Text</ResourceName>
    <Hidden>false</Hidden>
  </Properties>
  <Properties>
    <Component>MDIParent1.cs</Component>
    <Name>selectAllToolStripMenuItem.Text</Name>
    <StringID>46</StringID>
    <Selected>true</Selected>
    <ResourceName>selectAllToolStripMenuItem.Text</ResourceName>
    <Hidden>false</Hidden>
  </Properties>
  <Properties>
    <Component>MDIParent1.cs</Component>
    <Name>editMenu.Text</Name>
    <StringID>47</StringID>
    <Selected>true</Selected>
    <ResourceName>editMenu.Text</ResourceName>
    <Hidden>false</Hidden>
  </Properties>
  <Properties>
    <Component>MDIParent1.cs</Component>
    <Name>toolBarToolStripMenuItem.Text</Name>
    <StringID>48</StringID>
    <Selected>true</Selected>
    <ResourceName>toolBarToolStripMenuItem.Text</ResourceName>
    <Hidden>false</Hidden>
  </Properties>
  <Properties>
    <Component>MDIParent1.cs</Component>
    <Name>statusBarToolStripMenuItem.Text</Name>
    <StringID>49</StringID>
    <Selected>true</Selected>
    <ResourceName>statusBarToolStripMenuItem.Text</ResourceName>
    <Hidden>false</Hidden>
  </Properties>
  <Properties>
    <Component>MDIParent1.cs</Component>
    <Name>viewMenu.Text</Name>
    <StringID>50</StringID>
    <Selected>true</Selected>
    <ResourceName>viewMenu.Text</ResourceName>
    <Hidden>false</Hidden>
  </Properties>
  <Properties>
    <Component>MDIParent1.cs</Component>
    <Name>optionsToolStripMenuItem.Text</Name>
    <StringID>51</StringID>
    <Selected>true</Selected>
    <ResourceName>optionsToolStripMenuItem.Text</ResourceName>
    <Hidden>false</Hidden>
  </Properties>
  <Properties>
    <Component>MDIParent1.cs</Component>
    <Name>toolsMenu.Text</Name>
    <StringID>52</StringID>
    <Selected>true</Selected>
    <ResourceName>toolsMenu.Text</ResourceName>
    <Hidden>false</Hidden>
  </Properties>
  <Properties>
    <Component>MDIParent1.cs</Component>
    <Name>newWindowToolStripMenuItem.Text</Name>
    <StringID>53</StringID>
    <Selected>true</Selected>
    <ResourceName>newWindowToolStripMenuItem.Text</ResourceName>
    <Hidden>false</Hidden>
  </Properties>
  <Properties>
    <Component>MDIParent1.cs</Component>
    <Name>cascadeToolStripMenuItem.Text</Name>
    <StringID>54</StringID>
    <Selected>true</Selected>
    <ResourceName>cascadeToolStripMenuItem.Text</ResourceName>
    <Hidden>false</Hidden>
  </Properties>
  <Properties>
    <Component>MDIParent1.cs</Component>
    <Name>tileVerticalToolStripMenuItem.Text</Name>
    <StringID>55</StringID>
    <Selected>true</Selected>
    <ResourceName>tileVerticalToolStripMenuItem.Text</ResourceName>
    <Hidden>false</Hidden>
  </Properties>
  <Properties>
    <Component>MDIParent1.cs</Component>
    <Name>tileHorizontalToolStripMenuItem.Text</Name>
    <StringID>56</StringID>
    <Selected>true</Selected>
    <ResourceName>tileHorizontalToolStripMenuItem.Text</ResourceName>
    <Hidden>false</Hidden>
  </Properties>
  <Properties>
    <Component>MDIParent1.cs</Component>
    <Name>closeAllToolStripMenuItem.Text</Name>
    <StringID>57</StringID>
    <Selected>true</Selected>
    <ResourceName>closeAllToolStripMenuItem.Text</ResourceName>
    <Hidden>false</Hidden>
  </Properties>
  <Properties>
    <Component>MDIParent1.cs</Component>
    <Name>arrangeIconsToolStripMenuItem.Text</Name>
    <StringID>58</StringID>
    <Selected>true</Selected>
    <ResourceName>arrangeIconsToolStripMenuItem.Text</ResourceName>
    <Hidden>false</Hidden>
  </Properties>
  <Properties>
    <Component>MDIParent1.cs</Component>
    <Name>windowsMenu.Text</Name>
    <StringID>59</StringID>
    <Selected>true</Selected>
    <ResourceName>windowsMenu.Text</ResourceName>
    <Hidden>false</Hidden>
  </Properties>
  <Properties>
    <Component>MDIParent1.cs</Component>
    <Name>tab2ToolStripMenuItem.Text</Name>
    <StringID>119</StringID>
    <Selected>true</Selected>
    <ResourceName>tab2ToolStripMenuItem.Text</ResourceName>
    <Hidden>false</Hidden>
  </Properties>
  <Properties>
    <Component>MDIParent1.cs</Component>
    <Name>tab23ToolStripMenuItem.Text</Name>
    <StringID>120</StringID>
    <Selected>true</Selected>
    <ResourceName>tab23ToolStripMenuItem.Text</ResourceName>
    <Hidden>false</Hidden>
  </Properties>
  <Properties>
    <Component>MDIParent1.cs</Component>
    <Name>tab24ToolStripMenuItem.Text</Name>
    <StringID>121</StringID>
    <Selected>true</Selected>
    <ResourceName>tab24ToolStripMenuItem.Text</ResourceName>
    <Hidden>false</Hidden>
  </Properties>
  <Properties>
    <Component>MDIParent1.cs</Component>
    <Name>dicToolStripMenuItem.Text</Name>
    <StringID>63</StringID>
    <Selected>true</Selected>
    <ResourceName>dicToolStripMenuItem.Text</ResourceName>
    <Hidden>false</Hidden>
  </Properties>
  <Properties>
    <Component>MDIParent1.cs</Component>
    <Name>contentsToolStripMenuItem.Text</Name>
    <StringID>64</StringID>
    <Selected>true</Selected>
    <ResourceName>contentsToolStripMenuItem.Text</ResourceName>
    <Hidden>false</Hidden>
  </Properties>
  <Properties>
    <Component>MDIParent1.cs</Component>
    <Name>indexToolStripMenuItem.Text</Name>
    <StringID>65</StringID>
    <Selected>true</Selected>
    <ResourceName>indexToolStripMenuItem.Text</ResourceName>
    <Hidden>false</Hidden>
  </Properties>
  <Properties>
    <Component>MDIParent1.cs</Component>
    <Name>searchToolStripMenuItem.Text</Name>
    <StringID>66</StringID>
    <Selected>true</Selected>
    <ResourceName>searchToolStripMenuItem.Text</ResourceName>
    <Hidden>false</Hidden>
  </Properties>
  <Properties>
    <Component>MDIParent1.cs</Component>
    <Name>aboutToolStripMenuItem.Text</Name>
    <StringID>67</StringID>
    <Selected>true</Selected>
    <ResourceName>aboutToolStripMenuItem.Text</ResourceName>
    <Hidden>false</Hidden>
  </Properties>
  <Properties>
    <Component>MDIParent1.cs</Component>
    <Name>helpMenu.Text</Name>
    <StringID>68</StringID>
    <Selected>true</Selected>
    <ResourceName>helpMenu.Text</ResourceName>
    <Hidden>false</Hidden>
  </Properties>
  <Properties>
    <Component>MDIParent1.cs</Component>
    <Name>menuStrip.Text</Name>
    <StringID>69</StringID>
    <Selected>true</Selected>
    <ResourceName>menuStrip.Text</ResourceName>
    <Hidden>false</Hidden>
  </Properties>
  <Properties>
    <Component>MDIParent1.cs</Component>
    <Name>newToolStripButton.Text</Name>
    <StringID>70</StringID>
    <Selected>true</Selected>
    <ResourceName>newToolStripButton.Text</ResourceName>
    <Hidden>false</Hidden>
  </Properties>
  <Properties>
    <Component>MDIParent1.cs</Component>
    <Name>newToolStripButton.ToolTipText</Name>
    <StringID>70</StringID>
    <Selected>true</Selected>
    <ResourceName>newToolStripButton.ToolTipText</ResourceName>
    <Hidden>false</Hidden>
  </Properties>
  <Properties>
    <Component>MDIParent1.cs</Component>
    <Name>openToolStripButton.Text</Name>
    <StringID>71</StringID>
    <Selected>true</Selected>
    <ResourceName>openToolStripButton.Text</ResourceName>
    <Hidden>false</Hidden>
  </Properties>
  <Properties>
    <Component>MDIParent1.cs</Component>
    <Name>openToolStripButton.ToolTipText</Name>
    <StringID>71</StringID>
    <Selected>true</Selected>
    <ResourceName>openToolStripButton.ToolTipText</ResourceName>
    <Hidden>false</Hidden>
  </Properties>
  <Properties>
    <Component>MDIParent1.cs</Component>
    <Name>saveToolStripButton.Text</Name>
    <StringID>72</StringID>
    <Selected>true</Selected>
    <ResourceName>saveToolStripButton.Text</ResourceName>
    <Hidden>false</Hidden>
  </Properties>
  <Properties>
    <Component>MDIParent1.cs</Component>
    <Name>saveToolStripButton.ToolTipText</Name>
    <StringID>72</StringID>
    <Selected>true</Selected>
    <ResourceName>saveToolStripButton.ToolTipText</ResourceName>
    <Hidden>false</Hidden>
  </Properties>
  <Properties>
    <Component>MDIParent1.cs</Component>
    <Name>printToolStripButton.Text</Name>
    <StringID>73</StringID>
    <Selected>true</Selected>
    <ResourceName>printToolStripButton.Text</ResourceName>
    <Hidden>false</Hidden>
  </Properties>
  <Properties>
    <Component>MDIParent1.cs</Component>
    <Name>printToolStripButton.ToolTipText</Name>
    <StringID>73</StringID>
    <Selected>true</Selected>
    <ResourceName>printToolStripButton.ToolTipText</ResourceName>
    <Hidden>false</Hidden>
  </Properties>
  <Properties>
    <Component>MDIParent1.cs</Component>
    <Name>printPreviewToolStripButton.Text</Name>
    <StringID>74</StringID>
    <Selected>true</Selected>
    <ResourceName>printPreviewToolStripButton.Text</ResourceName>
    <Hidden>false</Hidden>
  </Properties>
  <Properties>
    <Component>MDIParent1.cs</Component>
    <Name>printPreviewToolStripButton.ToolTipText</Name>
    <StringID>74</StringID>
    <Selected>true</Selected>
    <ResourceName>printPreviewToolStripButton.ToolTipText</ResourceName>
    <Hidden>false</Hidden>
  </Properties>
  <Properties>
    <Component>MDIParent1.cs</Component>
    <Name>helpToolStripButton.Text</Name>
    <StringID>75</StringID>
    <Selected>true</Selected>
    <ResourceName>helpToolStripButton.Text</ResourceName>
    <Hidden>false</Hidden>
  </Properties>
  <Properties>
    <Component>MDIParent1.cs</Component>
    <Name>helpToolStripButton.ToolTipText</Name>
    <StringID>75</StringID>
    <Selected>true</Selected>
    <ResourceName>helpToolStripButton.ToolTipText</ResourceName>
    <Hidden>false</Hidden>
  </Properties>
  <Properties>
    <Component>MDIParent1.cs</Component>
    <Name>toolStrip.Text</Name>
    <StringID>76</StringID>
    <Selected>true</Selected>
    <ResourceName>toolStrip.Text</ResourceName>
    <Hidden>false</Hidden>
  </Properties>
  <Properties>
    <Component>MDIParent1.cs</Component>
    <Name>toolStripStatusLabel.Text</Name>
    <StringID>77</StringID>
    <Selected>true</Selected>
    <ResourceName>toolStripStatusLabel.Text</ResourceName>
    <Hidden>false</Hidden>
  </Properties>
  <Properties>
    <Component>MDIParent1.cs</Component>
    <Name>statusStrip.Text</Name>
    <StringID>78</StringID>
    <Selected>true</Selected>
    <ResourceName>statusStrip.Text</ResourceName>
    <Hidden>false</Hidden>
  </Properties>
  <Properties>
    <Component>AboutBox1.cs</Component>
    <Name>$this.Text</Name>
    <StringID>1</StringID>
    <Selected>true</Selected>
    <ResourceName>$this.Text</ResourceName>
    <Hidden>false</Hidden>
  </Properties>
  <Properties>
    <Component>Form1.cs</Component>
    <Name>$this.Text</Name>
    <StringID>8</StringID>
    <Selected>true</Selected>
    <ResourceName>$this.Text</ResourceName>
    <Hidden>false</Hidden>
  </Properties>
  <Properties>
    <Component>Form2.cs</Component>
    <Name>$this.Text</Name>
    <StringID>25</StringID>
    <Selected>true</Selected>
    <ResourceName>$this.Text</ResourceName>
    <Hidden>false</Hidden>
  </Properties>
  <Properties>
    <Component>Form3.cs</Component>
    <Name>$this.Text</Name>
    <StringID>26</StringID>
    <Selected>true</Selected>
    <ResourceName>$this.Text</ResourceName>
    <Hidden>false</Hidden>
  </Properties>
  <Properties>
    <Component>Form5.cs</Component>
    <Name>$this.Text</Name>
    <StringID>27</StringID>
    <Selected>true</Selected>
    <ResourceName>$this.Text</ResourceName>
    <Hidden>false</Hidden>
  </Properties>
  <Properties>
    <Component>MDIParent1.cs</Component>
    <Name>$this.Text</Name>
    <StringID>28</StringID>
    <Selected>true</Selected>
    <ResourceName>$this.Text</ResourceName>
    <Hidden>false</Hidden>
  </Properties>
  <Properties>
    <Component>Form6.cs</Component>
    <Name>key_Label.Text</Name>
    <StringID>97</StringID>
    <Selected>true</Selected>
    <ResourceName>key_Label.Text</ResourceName>
    <Hidden>false</Hidden>
  </Properties>
  <Properties>
    <Component>Form6.cs</Component>
    <Name>kprLabel.Text</Name>
    <StringID>98</StringID>
    <Selected>true</Selected>
    <ResourceName>kprLabel.Text</ResourceName>
    <Hidden>false</Hidden>
  </Properties>
  <Properties>
    <Component>Form6.cs</Component>
    <Name>kupLabel.Text</Name>
    <StringID>99</StringID>
    <Selected>true</Selected>
    <ResourceName>kupLabel.Text</ResourceName>
    <Hidden>false</Hidden>
  </Properties>
  <Properties>
    <Component>Form6.cs</Component>
    <Name>terminLabel.Text</Name>
    <StringID>100</StringID>
    <Selected>true</Selected>
    <ResourceName>terminLabel.Text</ResourceName>
    <Hidden>false</Hidden>
  </Properties>
  <Properties>
    <Component>Form6.cs</Component>
    <Name>index_nLabel.Text</Name>
    <StringID>101</StringID>
    <Selected>true</Selected>
    <ResourceName>index_nLabel.Text</ResourceName>
    <Hidden>false</Hidden>
  </Properties>
  <Properties>
    <Component>Form6.cs</Component>
    <Name>index_vLabel.Text</Name>
    <StringID>102</StringID>
    <Selected>true</Selected>
    <ResourceName>index_vLabel.Text</ResourceName>
    <Hidden>false</Hidden>
  </Properties>
  <Properties>
    <Component>Form6.cs</Component>
    <Name>bindingNavigatorAddNewItem.Text</Name>
    <StringID>103</StringID>
    <Selected>true</Selected>
    <ResourceName>bindingNavigatorAddNewItem.Text</ResourceName>
    <Hidden>false</Hidden>
  </Properties>
  <Properties>
    <Component>Form6.cs</Component>
    <Name>bindingNavigatorCountItem.Text</Name>
    <StringID>104</StringID>
    <Selected>true</Selected>
    <ResourceName>bindingNavigatorCountItem.Text</ResourceName>
    <Hidden>false</Hidden>
  </Properties>
  <Properties>
    <Component>Form6.cs</Component>
    <Name>bindingNavigatorCountItem.ToolTipText</Name>
    <StringID>105</StringID>
    <Selected>true</Selected>
    <ResourceName>bindingNavigatorCountItem.ToolTipText</ResourceName>
    <Hidden>false</Hidden>
  </Properties>
  <Properties>
    <Component>Form6.cs</Component>
    <Name>bindingNavigatorDeleteItem.Text</Name>
    <StringID>106</StringID>
    <Selected>true</Selected>
    <ResourceName>bindingNavigatorDeleteItem.Text</ResourceName>
    <Hidden>false</Hidden>
  </Properties>
  <Properties>
    <Component>Form6.cs</Component>
    <Name>bindingNavigatorMoveFirstItem.Text</Name>
    <StringID>107</StringID>
    <Selected>true</Selected>
    <ResourceName>bindingNavigatorMoveFirstItem.Text</ResourceName>
    <Hidden>false</Hidden>
  </Properties>
  <Properties>
    <Component>Form6.cs</Component>
    <Name>bindingNavigatorMovePreviousItem.Text</Name>
    <StringID>108</StringID>
    <Selected>true</Selected>
    <ResourceName>bindingNavigatorMovePreviousItem.Text</ResourceName>
    <Hidden>false</Hidden>
  </Properties>
  <Properties>
    <Component>Form6.cs</Component>
    <Name>bindingNavigatorPositionItem.AccessibleName</Name>
    <StringID>109</StringID>
    <Selected>true</Selected>
    <ResourceName>bindingNavigatorPositionItem.AccessibleName</ResourceName>
    <Hidden>false</Hidden>
  </Properties>
  <Properties>
    <Component>Form6.cs</Component>
    <Name>bindingNavigatorPositionItem.Text</Name>
    <StringID>22</StringID>
    <Selected>true</Selected>
    <ResourceName>bindingNavigatorPositionItem.Text</ResourceName>
    <Hidden>false</Hidden>
  </Properties>
  <Properties>
    <Component>Form6.cs</Component>
    <Name>bindingNavigatorPositionItem.ToolTipText</Name>
    <StringID>110</StringID>
    <Selected>true</Selected>
    <ResourceName>bindingNavigatorPositionItem.ToolTipText</ResourceName>
    <Hidden>false</Hidden>
  </Properties>
  <Properties>
    <Component>Form6.cs</Component>
    <Name>bindingNavigatorMoveNextItem.Text</Name>
    <StringID>111</StringID>
    <Selected>true</Selected>
    <ResourceName>bindingNavigatorMoveNextItem.Text</ResourceName>
    <Hidden>false</Hidden>
  </Properties>
  <Properties>
    <Component>Form6.cs</Component>
    <Name>bindingNavigatorMoveLastItem.Text</Name>
    <StringID>112</StringID>
    <Selected>true</Selected>
    <ResourceName>bindingNavigatorMoveLastItem.Text</ResourceName>
    <Hidden>false</Hidden>
  </Properties>
  <Properties>
    <Component>Form6.cs</Component>
    <Name>tab2BindingNavigatorSaveItem.Text</Name>
    <StringID>113</StringID>
    <Selected>true</Selected>
    <ResourceName>tab2BindingNavigatorSaveItem.Text</ResourceName>
    <Hidden>false</Hidden>
  </Properties>
  <Properties>
    <Component>Form6.cs</Component>
    <Name>tab2BindingNavigator.Text</Name>
    <StringID>114</StringID>
    <Selected>true</Selected>
    <ResourceName>tab2BindingNavigator.Text</ResourceName>
    <Hidden>false</Hidden>
  </Properties>
  <Properties>
    <Component>Form6.cs</Component>
    <Name>$this.Text</Name>
    <StringID>115</StringID>
    <Selected>true</Selected>
    <ResourceName>$this.Text</ResourceName>
    <Hidden>false</Hidden>
  </Properties>
  <Properties>
    <Component>Form7.cs</Component>
    <Name>$this.Text</Name>
    <StringID>116</StringID>
    <Selected>true</Selected>
    <ResourceName>$this.Text</ResourceName>
    <Hidden>false</Hidden>
  </Properties>
  <Properties>
    <Component>Form8.cs</Component>
    <Name>$this.Text</Name>
    <StringID>117</StringID>
    <Selected>true</Selected>
    <ResourceName>$this.Text</ResourceName>
    <Hidden>false</Hidden>
  </Properties>
  <GeneralAttributes>
    <Name>StatusHash</Name>
    <TextValue>Bf5AV1MWbxJVWefJrFWGVPEHx+k=</TextValue>
    <NumValue>0</NumValue>
  </GeneralAttributes>
  <GeneralAttributes>
    <Name>XmlDatabaseVersion</Name>
    <TextValue>1</TextValue>
    <NumValue>1</NumValue>
  </GeneralAttributes>
  <GeneralAttributes>
    <Name>Dirty</Name>
    <TextValue>False</TextValue>
    <NumValue>0</NumValue>
  </GeneralAttributes>
  <GeneralAttributes>
    <Name>UseNamedResources</Name>
    <TextValue>True</TextValue>
    <NumValue>1</NumValue>
  </GeneralAttributes>
  <GeneralAttributes>
    <Name>GenerateMultilangResx</Name>
    <TextValue>False</TextValue>
    <NumValue>0</NumValue>
  </GeneralAttributes>
  <GeneralAttributes>
    <Name>OriginalLanguageIetfTag</Name>
    <TextValue>en</TextValue>
    <NumValue>0</NumValue>
  </GeneralAttributes>
  <GeneralAttributes>
    <Name>MaxMLIdForXaml</Name>
    <TextValue>-1</TextValue>
    <NumValue>-1</NumValue>
  </GeneralAttributes>
  <GeneralAttributes>
    <Name>AlwaysRescanControls</Name>
    <TextValue>False</TextValue>
    <NumValue>0</NumValue>
  </GeneralAttributes>
  <GeneralAttributes>
    <Name>AlwaysRescanSource</Name>
    <TextValue>False</TextValue>
    <NumValue>0</NumValue>
  </GeneralAttributes>
</MdbTranslationStore>